vsdkx_model_yolo_torch-1.0-py3.10-nspkg.pth
vsdkx/model/yolo_torch/__init__.py
vsdkx/model/yolo_torch/driver.py
vsdkx/model/yolo_torch/settings.py
vsdkx_model_yolo_torch-1.0.dist-info/LICENSE
vsdkx_model_yolo_torch-1.0.dist-info/METADATA
vsdkx_model_yolo_torch-1.0.dist-info/WHEEL
vsdkx_model_yolo_torch-1.0.dist-info/dependency_links.txt
vsdkx_model_yolo_torch-1.0.dist-info/namespace_packages.txt
vsdkx_model_yolo_torch-1.0.dist-info/top_level.txt
vsdkx_model_yolo_torch-1.0.dist-info/RECORD
