Metadata-Version: 2.1
Name: vsdkx-model-yolo-torch
Version: 1.0
Summary: UNKNOWN
Home-page: https://github.com/natix-io/vsdkx-model-yolo-torch.git
Author: Helmut
Author-email: helmut@natix.io
License: UNKNOWN
Platform: UNKNOWN
License-File: LICENSE
Requires-Dist: vsdkx-core
Requires-Dist: torch (>=1.7.0)
Requires-Dist: torchvision (>=0.8.1)
Requires-Dist: pandas
Requires-Dist: tqdm (>=4.41.0)
Requires-Dist: matplotlib (>=3.2.2)
Requires-Dist: seaborn (>=0.11.0)
Requires-Dist: numpy (>=1.18.5)
